myfmt/__init__.py
myfmt/generator.py
myfmt/reader.py
myfmt/writer.py
myfmt/data/MYFMT_README.md
myfmt/data/example.myfmt
myfmt_reader-1.0.0.dist-info/METADATA
myfmt_reader-1.0.0.dist-info/WHEEL
myfmt_reader-1.0.0.dist-info/top_level.txt
myfmt_reader-1.0.0.dist-info/RECORD
